{
	"configurations" : 
	[
		{
			"directories" : 
			[
				{
					"build" : ".",
					"jsonFile" : "directory-.-Debug-f5ebdc15457944623624.json",
					"minimumCMakeVersion" : 
					{
						"string" : "3.28"
					},
					"projectIndex" : 0,
					"source" : ".",
					"targetIndexes" : 
					[
						0,
						1,
						2
					]
				}
			],
			"name" : "Debug",
			"projects" : 
			[
				{
					"directoryIndexes" : 
					[
						0
					],
					"name" : "aio",
					"targetIndexes" : 
					[
						0,
						1,
						2
					]
				}
			],
			"targets" : 
			[
				{
					"directoryIndex" : 0,
					"id" : "io_uring_ctx::@6890427a1f51a3e7e1df",
					"jsonFile" : "target-io_uring_ctx-Debug-d12b519f5b48464044e7.json",
					"name" : "io_uring_ctx",
					"projectIndex" : 0
				},
				{
					"directoryIndex" : 0,
					"id" : "main::@6890427a1f51a3e7e1df",
					"jsonFile" : "target-main-Debug-102e4a116c23e4c39760.json",
					"name" : "main",
					"projectIndex" : 0
				},
				{
					"directoryIndex" : 0,
					"id" : "tcp_server::@6890427a1f51a3e7e1df",
					"jsonFile" : "target-tcp_server-Debug-4248500217d22c818bf8.json",
					"name" : "tcp_server",
					"projectIndex" : 0
				}
			]
		}
	],
	"kind" : "codemodel",
	"paths" : 
	{
		"build" : "/home/ynachi/codes/aio/cmake-build-debug",
		"source" : "/home/ynachi/codes/aio"
	},
	"version" : 
	{
		"major" : 2,
		"minor" : 7
	}
}
